smart_pr_generator/ __init__.py
smart_pr_generator/agents.py
smart_pr_generator/config.py
smart_pr_generator/helpers/__init__.py
smart_pr_generator/helpers/get_git_info.py
smart_pr_generator/helpers/get_pull_request_template.py
smart_pr_generator/helpers/github_client.py
smart_pr_generator/helpers/is_tool_calling.py
smart_pr_generator/helpers/jira_client.py
smart_pr_generator/main.py
smart_pr_generator/prompts.py
smart_pr_generator/tools.py
smart_pr_generator-0.1.15.dist-info/LICENSE
smart_pr_generator-0.1.15.dist-info/METADATA
smart_pr_generator-0.1.15.dist-info/WHEEL
smart_pr_generator-0.1.15.dist-info/entry_points.txt
smart_pr_generator-0.1.15.dist-info/RECORD
