Metadata-Version: 2.1
Name: smart-pr-generator
Version: 0.1.15
Summary: A short description of your package
Author: jeongsk
Author-email: jeongseok@wantedlab.com
Requires-Python: >=3.9
Classifier: Programming Language :: Python :: 3
Classifier: Programming Language :: Python :: 3.9
Classifier: Programming Language :: Python :: 3.10
Classifier: Programming Language :: Python :: 3.11
Classifier: Programming Language :: Python :: 3.12
Classifier: Programming Language :: Python :: 3.13
Requires-Dist: jira (>=3.8.0,<4.0.0)
Requires-Dist: langchain-community (>=0.3.5,<0.4.0)
Requires-Dist: langchain-core (>=0.3.15,<0.4.0)
Requires-Dist: langchain-openai (>=0.2.6,<0.3.0)
Requires-Dist: packaging (>=24.2,<25.0)
Requires-Dist: python-dotenv (>=1.0.1,<2.0.0)
Requires-Dist: requests (>=2.32.3,<3.0.0)
Requires-Dist: tomli (>=2.1.0,<3.0.0)
